ormic/__init__.py
ormic/database.py
ormic/exceptions.py
ormic/field.py
ormic/model.py
ormic-1.0.0.dist-info/LICENSE.txt
ormic-1.0.0.dist-info/METADATA
ormic-1.0.0.dist-info/WHEEL
ormic-1.0.0.dist-info/top_level.txt
ormic-1.0.0.dist-info/RECORD
