Metadata-Version: 2.1
Name: ormic
Version: 1.0.0
Summary: A simple, asynchronous python ORM for SQLite databases
Home-page: https://github.com/Dorukyum/ormic
Author: Dorukyum
License: MIT
Project-URL: Source, https://github.com/Dorukyum/ormic
Keywords: database,ORM
Platform: UNKNOWN
Classifier: License :: OSI Approved :: MIT License
Classifier: Programming Language :: Python :: 3
License-File: LICENSE.txt
Requires-Dist: aiosqlite
